sebs/__init__.py
sebs/app.py
sebs/cli.py
sebs/ec2.py
sebs-0.5.1.data/scripts/sebs
tests/__init__.py
tests/functional/__init__.py
tests/functional/test_sebs.py
tests/unit/__init__.py
tests/unit/test_cli.py
tests/unit/test_instance.py
tests/unit/test_main.py
tests/unit/test_stateful_volume.py
tests/utils/__init__.py
tests/utils/aws_utils.py
sebs-0.5.1.dist-info/LICENSE
sebs-0.5.1.dist-info/METADATA
sebs-0.5.1.dist-info/WHEEL
sebs-0.5.1.dist-info/top_level.txt
sebs-0.5.1.dist-info/RECORD
