Metadata-Version: 2.1
Name: sebs
Version: 0.5.1
Summary: Create Stateful Elastic Block Storage on AWS.
Home-page: https://github.com/DontShaveTheYak/sebs
Author: Levi Blaney
Author-email: shadycuz@gmail.com
License: UNKNOWN
Platform: UNKNOWN
Classifier: License :: OSI Approved :: GNU General Public License v3 (GPLv3)
Classifier: Operating System :: POSIX :: Linux
Classifier: Development Status :: 4 - Beta
Classifier: Intended Audience :: Developers
Classifier: Intended Audience :: System Administrators
Classifier: Natural Language :: English
Classifier: Programming Language :: Python :: 3.6
Classifier: Programming Language :: Python :: 3.7
Classifier: Programming Language :: Python :: 3.8
Requires-Python: >=3.6
Requires-Dist: boto3
Requires-Dist: ec2-metadata
Requires-Dist: importlib-metadata (~=1.0) ; python_version < "3.8"
